{
    "details": [
        {
            "name": "Ultrasonography",
            "doctor": "Sadik khan",
            "day": "Everyday",
            "fees": 900,
            "id": 1
        },
        {
            "name": "City Scan",
            "doctor": "Nazmul Huda",
            "day": "Everyday",
            "fees": 4900,
            "id": 2
        },
        {
            "name": "Radiotherapy",
            "doctor": "Alauddin khan",
            "day": "friday, sunday, tuesday",
            "fees": 3400,
            "id": 3
        },
        {
            "name": "Brain Cancer",
            "doctor": "Rahul Hassan",
            "day": "monday, tuesday",
            "fees": 9900,
            "id": 4
        },
        {
            "name": "Cesarean delivery",
            "doctor": "Masud Karim",
            "day": "Everyday",
            "fees": 23000,
            "id": 5
        },
        {
            "name": "Eye Check-Up",
            "doctor": "Mostafizur",
            "day": "Everyday",
            "fees": 1300,
            "id": 6
        },
        {
            "name": "Heart Surgery",
            "doctor": "Rassel hossain",
            "day": "Friday, Monday",
            "fees": 3300,
            "id": 7
        },
        {
            "name": "X-Ray",
            "doctor": "Naeem Hassan",
            "day": "Everyday",
            "fees": 3900,
            "id": 8
        },
        {
            "name": "Apendicitis Operation",
            "doctor": "Naeem Adnan",
            "day": "Tuesday, Saturday",
            "fees": 26900,
            "id": 9
        },
        {
            "name": "Kidney check-up",
            "doctor": "Solaiman Ali",
            "day": "Sunday, Wednesday",
            "fees": 21000,
            "id": 10
        }
    ]
}